lib/102116058.py
lib/__init__.py
Topsis_Naman_102116058-1.0.6.dist-info/METADATA
Topsis_Naman_102116058-1.0.6.dist-info/WHEEL
Topsis_Naman_102116058-1.0.6.dist-info/top_level.txt
Topsis_Naman_102116058-1.0.6.dist-info/RECORD
